blobs/__init__.py
blobs/bin/imgpkg
blobs-0.0.8.dist-info/LICENSE
blobs-0.0.8.dist-info/METADATA
blobs-0.0.8.dist-info/WHEEL
blobs-0.0.8.dist-info/top_level.txt
blobs-0.0.8.dist-info/RECORD
