Metadata-Version: 2.1
Name: blobs
Version: 0.0.8
Summary: Artifact storage using OCI registries
Home-page: https://github.com/aunum/blobs
Maintainer: Patrick Barker
Project-URL: Documentation, https://github.com/aunum/blobs
Project-URL: Code, https://github.com/aunum/blobs
Project-URL: Issue tracker, https://github.com/aunum/blobs
Requires-Python: >=3.6
License-File: LICENSE
Requires-Dist: jsonpickle
